obsipub/__init__.py
obsipub/cli.py
obsipub/converter.py
obsipub/file_scanner.py
obsipub/markdown_processor.py
obsipub/utils.py
obsipub-1.0.1.dist-info/licenses/LICENSE
obsipub-1.0.1.dist-info/METADATA
obsipub-1.0.1.dist-info/WHEEL
obsipub-1.0.1.dist-info/entry_points.txt
obsipub-1.0.1.dist-info/top_level.txt
obsipub-1.0.1.dist-info/RECORD
