Metadata-Version: 2.4
Name: obsipub
Version: 1.0.1
Summary: Convert Obsidian vaults to EPUB format with proper chapter structure
Author-email: TCSenpai <tcsenpai@discus.sh>
Maintainer-email: TCSenpai <tcsenpai@discus.sh>
License: MIT License
Project-URL: Homepage, https://github.com/tcsenpai/obsipub
Project-URL: Repository, https://github.com/tcsenpai/obsipub.git
Project-URL: Issues, https://github.com/tcsenpai/obsipub/issues
Project-URL: Documentation, https://github.com/tcsenpai/obsipub#readme
Keywords: obsidian,epub,ebook,markdown,converter,knowledge-base
Classifier: Development Status :: 5 - Production/Stable
Classifier: Intended Audience :: End Users/Desktop
Classifier: Intended Audience :: Education
Classifier: Topic :: Text Processing :: Markup
Classifier: Topic :: Utilities
Classifier: License :: OSI Approved :: MIT License
Classifier: Programming Language :: Python :: 3
Classifier: Programming Language :: Python :: 3.7
Classifier: Programming Language :: Python :: 3.8
Classifier: Programming Language :: Python :: 3.9
Classifier: Programming Language :: Python :: 3.10
Classifier: Programming Language :: Python :: 3.11
Classifier: Programming Language :: Python :: 3.12
Classifier: Operating System :: OS Independent
Requires-Python: >=3.7
License-File: LICENSE
Requires-Dist: PyYAML>=5.4.0
Provides-Extra: dev
Requires-Dist: pytest>=6.0; extra == "dev"
Requires-Dist: pytest-cov; extra == "dev"
Requires-Dist: black; extra == "dev"
Requires-Dist: flake8; extra == "dev"
Requires-Dist: mypy; extra == "dev"
Requires-Dist: twine; extra == "dev"
Requires-Dist: build; extra == "dev"
Dynamic: license-file
Dynamic: requires-python
